ggctest/__init__.py
ggctest/decorators/singleton.py
ggctest/utils/dialog.py
ggctest-0.1.1.dist-info/WHEEL
ggctest-0.1.1.dist-info/entry_points.txt
ggctest-0.1.1.dist-info/METADATA
ggctest-0.1.1.dist-info/RECORD
